flask_sketch/__init__.py
flask_sketch/__main__.py
flask_sketch/config.py
flask_sketch/const/__init__.py
flask_sketch/const/requirements.py
flask_sketch/handlers/__init__.py
flask_sketch/handlers/api_auth_handler.py
flask_sketch/handlers/api_framework_handler.py
flask_sketch/handlers/app_type_handler.py
flask_sketch/handlers/auth_handler.py
flask_sketch/handlers/commands_handler.py
flask_sketch/handlers/config_handler.py
flask_sketch/handlers/database_handler.py
flask_sketch/handlers/features_handler.py
flask_sketch/handlers/models_handler.py
flask_sketch/make.py
flask_sketch/questions/__init__.py
flask_sketch/questions/api_framework.py
flask_sketch/questions/auth_framework.py
flask_sketch/questions/commom.py
flask_sketch/questions/config.py
flask_sketch/questions/const.py
flask_sketch/questions/features.py
flask_sketch/sketch.py
flask_sketch/templates/.gitignore_tpl
flask_sketch/templates/__init__.py
flask_sketch/templates/api/__init__.py
flask_sketch/templates/api/api_init_jwt_extended_tpl
flask_sketch/templates/api/api_init_noauth_tpl
flask_sketch/templates/api/api_init_restx_jwtext_tpl
flask_sketch/templates/api/api_init_restx_noauth_tpl
flask_sketch/templates/api/resources/__init__.py
flask_sketch/templates/api/resources/examples/__init__.py
flask_sketch/templates/api/resources/examples/api_example_smorest_pet_auth_tpl
flask_sketch/templates/api/resources/examples/api_example_smorest_pet_tpl
flask_sketch/templates/api/resources/examples/api_examples_restx_pet_auth_tpl
flask_sketch/templates/api/resources/examples/api_examples_restx_pet_tpl
flask_sketch/templates/app/__init__.py
flask_sketch/templates/app/app_dynaconf_conf_tpl
flask_sketch/templates/app/app_none_conf_framework_tpl
flask_sketch/templates/commands/__init__.py
flask_sketch/templates/commands/mongo_default_tpl
flask_sketch/templates/commands/mongo_noauth_tpl
flask_sketch/templates/commands/mongo_security_tpl
flask_sketch/templates/commands/sql_default_tpl
flask_sketch-0.3.29.dist-info/entry_points.txt
flask_sketch-0.3.29.dist-info/LICENSE
flask_sketch-0.3.29.dist-info/WHEEL
flask_sketch-0.3.29.dist-info/METADATA
flask_sketch-0.3.29.dist-info/RECORD
