Metadata-Version: 2.1
Name: flask-sketch
Version: 0.3.29
Summary: A CLI for autogenerate folder structure and boilerplate for Flask applications
Home-page: https://github.com/ericsouza/flask-sketch
License: MIT
Keywords: flask-sketch,flask_sketch,flask boilerplate
Author: Eric Souza
Author-email: ericsouza0801@gmail.com
Requires-Python: >=3.7,<4.0
Classifier: License :: OSI Approved :: MIT License
Classifier: Programming Language :: Python :: 3
Classifier: Programming Language :: Python :: 3.7
Classifier: Programming Language :: Python :: 3.8
Classifier: Programming Language :: Python :: 3.9
Requires-Dist: pyfiglet (>=0.8.post1,<0.9)
Requires-Dist: pyinquirer (>=1.0.3,<2.0.0)
Requires-Dist: toml (>=0.10.1,<0.11.0)
Project-URL: Repository, https://github.com/ericsouza/flask-sketch
